wonnx-0.5.1.dist-info/METADATA
wonnx-0.5.1.dist-info/WHEEL
wonnx/__init__.py
wonnx/wonnx.abi3.so
wonnx-0.5.1.dist-info/RECORD
