Metadata-Version: 2.1
Name: wonnx
Version: 0.5.1
Summary: Wonnx is an ONNX runtime based on wgpu aimed at being a universal GPU runtime, written in Rust.
Home-Page: https://github.com/webonnx/wonnx
Author: haixuanTao <tao.xavier@outlook.com>, Tommy van der Vorst <tommy@pixelspark.nl>
Author-email: haixuanTao <tao.xavier@outlook.com>, Tommy van der Vorst <tommy@pixelspark.nl>
License: MIT OR Apache-2.0
Requires-Python: >=3.7
Project-URL: Source Code, https://github.com/webonnx/wonnx.git
